dannychain/__init__.py
dannychain/__main__.py
dannychain/action.py
dannychain/auth.py
dannychain/cache.py
dannychain/chat_settings.py
dannychain/cli/__init__.py
dannychain/cli/utils.py
dannychain/config.py
dannychain/context.py
dannychain/data/__init__.py
dannychain/data/acl.py
dannychain/element.py
dannychain/emitter.py
dannychain/haystack/__init__.py
dannychain/haystack/callbacks.py
dannychain/hello.py
dannychain/input_widget.py
dannychain/langchain/__init__.py
dannychain/langchain/callbacks.py
dannychain/langflow/__init__.py
dannychain/llama_index/__init__.py
dannychain/llama_index/callbacks.py
dannychain/logger.py
dannychain/markdown.py
dannychain/message.py
dannychain/oauth_providers.py
dannychain/playground/__init__.py
dannychain/playground/config.py
dannychain/playground/provider.py
dannychain/playground/providers/__init__.py
dannychain/playground/providers/anthropic.py
dannychain/playground/providers/huggingface.py
dannychain/playground/providers/langchain.py
dannychain/playground/providers/openai.py
dannychain/playground/providers/vertexai.py
dannychain/py.typed
dannychain/secret.py
dannychain/server.py
dannychain/session.py
dannychain/socket.py
dannychain/step.py
dannychain/sync.py
dannychain/telemetry.py
dannychain/translations/en-US.json
dannychain/translations/pt-BR.json
dannychain/types.py
dannychain/user.py
dannychain/user_session.py
dannychain/utils.py
dannychain/version.py
dannychain-1.0.200.dist-info/entry_points.txt
dannychain-1.0.200.dist-info/METADATA
dannychain-1.0.200.dist-info/WHEEL
dannychain-1.0.200.dist-info/RECORD
